pyadb3/__init__.py
pyadb3/adb.py
pyadb3-1.0.2.dist-info/METADATA
pyadb3-1.0.2.dist-info/RECORD
pyadb3-1.0.2.dist-info/WHEEL
pyadb3-1.0.2.dist-info/top_level.txt
