Metadata-Version: 2.1
Name: pyadb3
Version: 1.0.2
Summary: Simple python module to interact with Android Debug Bridge tool
Home-page: https://github.com/mikusjelly/pyadb3
Author: mikusjelly
Author-email: mikusjelly@gmail.com
License: BSD
Keywords: python android adb
Platform: UNKNOWN
Classifier: Development Status :: 4 - Beta
Classifier: Topic :: Utilities
Classifier: Programming Language :: Python :: 3 :: Only
Classifier: License :: OSI Approved :: BSD License
